{"15": {"sequence": {"type": "str", "value": "AGCGTACGTAGATCGTACGT"}, "gc_content": {"type": "float", "value": 0.505095798180931}, "targets": {"type": "list", "value": [{"type": "str", "value": "phageA"}, {"type": "str", "value": "phageB"}, {"type": "str", "value": "phageC"}]}}, "14": {"sequence": {"type": "str", "value": "AGCGTACGTAGATCGTACGT"}, "gc_content": {"type": "float", "value": 0.5453784591094509}, "targets": {"type": "list", "value": [{"type": "str", "value": "phageC"}, {"type": "str", "value": "phageB"}]}}, "13": {"sequence": {"type": "str", "value": "AGCGTACGTAGATCGTACGT"}, "gc_content": {"type": "float", "value": 0.49136252852817797}, "targets": {"type": "list", "value": [{"type": "str", "value": "phageA"}]}}, "12": {"sequence": {"type": "str", "value": "AGCGTACGTAGATCGTACGT"}, "gc_content": {"type": "float", "value": 0.4112605944485462}, "targets": {"type": "list", "value": [{"type": "str", "value": "phageA"}, {"type": "str", "value": "phageC"}]}}, "11": {"sequence": {"type": "str", "value": "AGCGTACGTAGATCGTACGT"}, "gc_content": {"type": "float", "value": 0.4827489123366426}, "targets": {"type": "list", "value": [{"type": "str", "value": "phageC"}, {"type": "str", "value": "phageB"}, {"type": "str", "value": "phageA"}]}}, "10": {"sequence": {"type": "str", "value": "AGCGTACGTAGATCGTACGT"}, "gc_content": {"type": "float", "value": 0.49856839162694455}, "targets": {"type": "list", "value": [{"type": "str", "value": "phageB"}, {"type": "str", "value": "phageC"}, {"type": "str", "value": "phageA"}]}}, "9": {"sequence": {"type": "str", "value": "AGCGTACGTAGATCGTACGT"}, "gc_content": {"type": "float", "value": 0.5722746837341894}, "targets": {"type": "list", "value": [{"type": "str", "value": "phageB"}, {"type": "str", "value": "phageC"}]}}, "8": {"sequence": {"type": "str", "value": "AGCGTACGTAGATCGTACGT"}, "gc_content": {"type": "float", "value": 0.5294327208455408}, "targets": {"type": "list", "value": [{"type": "str", "value": "phageC"}, {"type": "str", "value": "phageB"}]}}, "7": {"sequence": {"type": "str", "value": "AGCGTACGTAGATCGTACGT"}, "gc_content": {"type": "float", "value": 0.5685038538049768}, "targets": {"type": "list", "value": [{"type": "str", "value": "phageC"}, {"type": "str", "value": "phageB"}, {"type": "str", "value": "phageA"}]}}, "6": {"sequence": {"type": "str", "value": "AGCGTACGTAGATCGTACGT"}, "gc_content": {"type": "float", "value": 0.4298304224730707}, "targets": {"type": "list", "value": [{"type": "str", "value": "phageA"}, {"type": "str", "value": "phageC"}, {"type": "str", "value": "phageB"}]}}, "5": {"sequence": {"type": "str", "value": "AGCGTACGTAGATCGTACGT"}, "gc_content": {"type": "float", "value": 0.46829237032795845}, "targets": {"type": "list", "value": [{"type": "str", "value": "phageC"}, {"type": "str", "value": "phageB"}, {"type": "str", "value": "phageA"}]}}, "4": {"sequence": {"type": "str", "value": "AGCGTACGTAGATCGTACGT"}, "gc_content": {"type": "float", "value": 0.5950266434938217}, "targets": {"type": "list", "value": [{"type": "str", "value": "phageB"}]}}, "3": {"sequence": {"type": "str", "value": "AGCGTACGTAGATCGTACGT"}, "gc_content": {"type": "float", "value": 0.4948133320177399}, "targets": {"type": "list", "value": [{"type": "str", "value": "phageB"}, {"type": "str", "value": "phageA"}, {"type": "str", "value": "phageC"}]}}, "2": {"sequence": {"type": "str", "value": "AGCGTACGTAGATCGTACGT"}, "gc_content": {"type": "float", "value": 0.45548513634624316}, "targets": {"type": "list", "value": [{"type": "str", "value": "phageA"}, {"type": "str", "value": "phageC"}, {"type": "str", "value": "phageB"}]}}, "1": {"sequence": {"type": "str", "value": "AGCGTACGTAGATCGTACGT"}, "gc_content": {"type": "float", "value": 0.46315439130305786}, "targets": {"type": "list", "value": [{"type": "str", "value": "phageA"}, {"type": "str", "value": "phageB"}]}}}